tests/__init__.py
tests/test_close.py
tests/test_copy.py
tests/test_delete.py
tests/test_getupdates.py
tests/test_history.py
tests/test_indexmod.py
tests/test_indices.py
tests/test_iterators.py
tests/test_rollback.py
tests/test_utils.py
tests/test_workload.py
treehaus/__init__.py
treehaus/index.py
treehaus/treehaus.py
treehaus/treebase/__init__.py
treehaus/treebase/btree.py
treehaus/treebase/pbtree.py
treehaus/treebase/player.py
treehaus-0.1.0.dist-info/LICENSE
treehaus-0.1.0.dist-info/METADATA
treehaus-0.1.0.dist-info/WHEEL
treehaus-0.1.0.dist-info/top_level.txt
treehaus-0.1.0.dist-info/RECORD
