Metadata-Version: 2.1
Name: treehaus
Version: 0.1.0
Summary: Python3 persistent balanced trees
Home-page: https://gitlab.com/treehaus/treehaus
Author: TreeHaus Developers
Author-email: 
License: OSI Approved :: Apache Software License
Keywords: data storage btree
Platform: UNKNOWN
Classifier: Development Status :: 3 - Alpha
Classifier: Intended Audience :: Developers
Classifier: Programming Language :: Python :: 3
Classifier: Programming Language :: Python :: 3.5
Requires-Python: >=3.5
